<?xml version="1.0" encoding="utf-8"?>
<ModMetadata xmlns:xsd="http://www.w3.org/2001/XMLSchema" xmlns:xsi="http://www.w3.org/2001/XMLSchema-instance">
  <Name>Satellite Pad Index</Name>
  <Author>Vespinian</Author>
  <Version>1.0.1</Version>
  <!-- Steam description using steam styling tags for Steam workshop page -->
  <Description>
    A plugin mod that adds extended Landingpad selection to Satellite Dishes.

    Uses BepInEx with StationeersLaunchPad.
    See: https://github.com/StationeersLaunchPad/StationeersLaunchPad

    The TargetPadIndex logic type now looks up Landingpad Data and Power Structures by Reference ID for easier pad selection.

    - Values 0-10: Vanilla behavior (selects by list index)
    - Values 11+: Value is treated as a "Landingpad Data and Power" Reference ID, the patch code of this plugin then tries to find that ID in the structures connected to the pads in the satellite's pad list defaulting to vanilla behavior if nothing is found.

    Repo: https://github.com/Vespinian/stationeers-pad-index
  </Description>
  <!-- Ingame Description using TMP tags for Workshop menu -->
  <!-- All contents of ChangeLog should be changed for each publication for Steam workshop page -->
  <ChangeLog>
    [h3]Version 1.0.1:[/h3]
    [list]
    [*]Updated thumbnail
    [/list]
    [h3]Version 1.0:[/h3]
    [list]
    [*]Initial release
    [/list]
  </ChangeLog>
  <!-- StationeersMods and BepInEx tags for Steam workshop page will be automatically added by the framework when publishing -->
  <WorkshopHandle>3697370095</WorkshopHandle>
  <Tags>
    <Tag>StationeersLaunchPad</Tag>
  </Tags>
  <!-- Automatic downloads of dependencies -->
  <Dependencies />
  <!-- Automatic reordering of the mods list -->
  <LoadBefore />
  <LoadAfter />
  <InGameDescription>
    <![CDATA[<size="30"><color=#ffa500> Satellite Pad Index </color></size>
A plugin mod that adds extended Landingpad selection to Satellite Dishes.

Uses BepInEx with StationeersLaunchPad.
See: https://github.com/StationeersLaunchPad/StationeersLaunchPad

The TargetPadIndex logic type now looks up Landingpad Data and Power Structures by Reference ID for easier pad selection.

- Values 0-10: Vanilla behavior (selects by list index)
- Values 11+: Value is treated as a "Landingpad Data and Power" Reference ID, the patch code of this plugin then tries to find that ID in the structures connected to the pads in the satellite's pad list defaulting to vanilla behavior if nothing is found.

Repo: https://github.com/Vespinian/stationeers-pad-index
]]>
  </InGameDescription>
</ModMetadata>
